{
    "mc": {
        "main": {
            "frameRate": 30,
            "events": [],
            "frames": [
                {
                    "res": "1788977718",
                    "x": -91.0,
                    "y": -116.0
                },
                {
                    "res": "3927714483",
                    "x": -126.0,
                    "y": -130.0
                },
                {
                    "res": "3165562668",
                    "x": -146.0,
                    "y": -148.0
                },
                {
                    "res": "1019712507",
                    "x": -165.0,
                    "y": -165.0
                },
                {
                    "res": "3687426240",
                    "x": -165.0,
                    "y": -165.0
                },
                {
                    "res": "2360653289",
                    "x": -105.0,
                    "y": -131.0
                },
                {
                    "res": "3003444880",
                    "x": -109.0,
                    "y": -134.0
                },
                {
                    "res": "2069918089",
                    "x": -113.0,
                    "y": -137.0
                },
                {
                    "res": "2344013493",
                    "x": -117.0,
                    "y": -140.0
                },
                {
                    "res": "2110581060",
                    "x": -121.0,
                    "y": -143.0
                },
                {
                    "res": "2537479697",
                    "x": -124.0,
                    "y": -146.0
                },
                {
                    "res": "2928380033",
                    "x": -128.0,
                    "y": -148.0
                },
                {
                    "res": "1373777735",
                    "x": -131.0,
                    "y": -150.0
                },
                {
                    "res": "3157369432",
                    "x": -135.0,
                    "y": -153.0
                },
                {
                    "res": "1034987313",
                    "x": -136.0,
                    "y": -133.0
                }
            ]
        }
    },
    "res": {
        "1788977718": {
            "x": 1727,
            "y": 330,
            "w": 188,
            "h": 201
        },
        "3927714483": {
            "x": 500,
            "y": 330,
            "w": 251,
            "h": 251
        },
        "3165562668": {
            "x": 659,
            "y": 0,
            "w": 290,
            "h": 291
        },
        "1019712507": {
            "x": 330,
            "y": 0,
            "w": 329,
            "h": 324
        },
        "3687426240": {
            "x": 0,
            "y": 0,
            "w": 330,
            "h": 330
        },
        "2360653289": {
            "x": 1505,
            "y": 330,
            "w": 222,
            "h": 237
        },
        "3003444880": {
            "x": 1275,
            "y": 330,
            "w": 230,
            "h": 243
        },
        "2069918089": {
            "x": 751,
            "y": 330,
            "w": 238,
            "h": 250
        },
        "2344013493": {
            "x": 254,
            "y": 330,
            "w": 246,
            "h": 257
        },
        "2110581060": {
            "x": 0,
            "y": 330,
            "w": 254,
            "h": 264
        },
        "2537479697": {
            "x": 1775,
            "y": 0,
            "w": 261,
            "h": 271
        },
        "2928380033": {
            "x": 1507,
            "y": 0,
            "w": 268,
            "h": 276
        },
        "1373777735": {
            "x": 1232,
            "y": 0,
            "w": 275,
            "h": 282
        },
        "3157369432": {
            "x": 949,
            "y": 0,
            "w": 283,
            "h": 289
        },
        "1034987313": {
            "x": 989,
            "y": 330,
            "w": 286,
            "h": 249
        }
    }
}